girder_worker/.gitignore
girder_worker/__init__.py
girder_worker/app.py
girder_worker/celeryconfig.py
girder_worker/entrypoint.py
girder_worker/log_utils.py
girder_worker/task.py
girder_worker/worker.dist.cfg
girder_worker/_test_plugins/__init__.py
girder_worker/_test_plugins/plugins.py
girder_worker/_test_plugins/tasks.py
girder_worker/context/__init__.py
girder_worker/context/girder_context.py
girder_worker/context/nongirder_context.py
girder_worker/docker/__init__.py
girder_worker/docker/nvidia.py
girder_worker/docker/stream_adapter.py
girder_worker/docker/utils.py
girder_worker/docker/io/__init__.py
girder_worker/docker/io/girder.py
girder_worker/docker/tasks/__init__.py
girder_worker/docker/transforms/__init__.py
girder_worker/docker/transforms/girder.py
girder_worker/utils/__init__.py
girder_worker/utils/decorators.py
girder_worker/utils/tee.py
girder_worker/utils/transform.py
girder_worker/utils/tests/__init__.py
girder_worker/utils/tests/decorators_test.py
girder_worker/utils/tests/girder_io_test.py
girder_worker/utils/tests/tee_test.py
girder_worker/utils/tests/transform_test.py
girder_worker/utils/tests/types_test.py
girder_worker/utils/tests/contrib/__init__.py
girder_worker/utils/tests/contrib/girder_io_test.py
girder_worker/utils/tests/fake_dir/file1.txt
girder_worker/utils/tests/fake_dir/file2.txt
girder_worker/utils/tests/fake_dir/subdir/file3.txt
girder_worker/utils/transforms/__init__.py
girder_worker/utils/transforms/common.py
girder_worker/utils/transforms/girder_io.py
girder_worker/utils/transforms/contrib/__init__.py
girder_worker/utils/transforms/contrib/girder_io.py
girder_worker/utils/types/__init__.py
girder_worker/utils/types/base.py
girder_worker/utils/types/boolean.py
girder_worker/utils/types/choice.py
girder_worker/utils/types/color.py
girder_worker/utils/types/girder.py
girder_worker/utils/types/girder_folder.py
girder_worker/utils/types/girder_item.py
girder_worker/utils/types/integer.py
girder_worker/utils/types/number.py
girder_worker-5.0.0a14.dev27.dist-info/METADATA
girder_worker-5.0.0a14.dev27.dist-info/WHEEL
girder_worker-5.0.0a14.dev27.dist-info/entry_points.txt
girder_worker-5.0.0a14.dev27.dist-info/top_level.txt
girder_worker-5.0.0a14.dev27.dist-info/RECORD
