Metadata-Version: 2.4
Name: girder-worker
Version: 5.0.0a14.dev27
Summary: Batch execution engine built on celery.
Home-page: https://github.com/girder/girder_worker
Author: Kitware, Inc.
Author-email: kitware@kitware.com
License: Apache 2.0
Classifier: Development Status :: 5 - Production/Stable
Classifier: Environment :: Console
Classifier: Operating System :: OS Independent
Classifier: Programming Language :: Python :: 3
Requires-Python: >=3.10
Requires-Dist: pyyaml>=4.2b1
Requires-Dist: Jinja2>=2.10.1
Requires-Dist: urllib3>=1.26.8
Requires-Dist: celery
Requires-Dist: girder-client>=5.0.0a5
Requires-Dist: pymongo>=3
Requires-Dist: requests[security]>=2.20.0
Requires-Dist: setuptools_scm
Requires-Dist: stevedore
Requires-Dist: jsonpickle
Requires-Dist: docker>=2.6.0
Dynamic: author
Dynamic: author-email
Dynamic: classifier
Dynamic: home-page
Dynamic: license
Dynamic: requires-dist
Dynamic: requires-python
Dynamic: summary
